openapi2jsonschema/__init__.py
openapi2jsonschema/command.py
openapi2jsonschema/errors.py
openapi2jsonschema/log.py
openapi2jsonschema/test_command.py
openapi2jsonschema/util.py
openapi2jsonschema-0.9.1.dist-info/entry_points.txt
openapi2jsonschema-0.9.1.dist-info/LICENSE
openapi2jsonschema-0.9.1.dist-info/WHEEL
openapi2jsonschema-0.9.1.dist-info/METADATA
openapi2jsonschema-0.9.1.dist-info/RECORD
