Metadata-Version: 2.1
Name: openapi2jsonschema
Version: 0.9.1
Summary: A utility to extract JSON Schema from a valid OpenAPI specification
Home-page: https://github.com/garethr/openapi2jsonschema
License: Apache-2.0
Keywords: openapi,jsonschema
Author: Gareth Rushgrove
Author-email: gareth@morethanseven.net
Requires-Python: >=3.7,<4.0
Classifier: License :: OSI Approved :: Apache Software License
Classifier: Programming Language :: Python :: 3
Classifier: Programming Language :: Python :: 3.7
Requires-Dist: click (>=7.0,<8.0)
Requires-Dist: colorama (>=0.4.1,<0.5.0)
Requires-Dist: jsonref (>=0.2.0,<0.3.0)
Requires-Dist: pyyaml (>=5.1,<6.0)
Project-URL: Repository, https://github.com/garethr/openapi2jsonschema
